{
  "settlementDate": {
    "year": 2020,
    "month": 3,
    "day": 20
  },
  "prices": [
    {
      "cfd": 125.51,
      "midp": 23.31
    },
    {
      "cfd": 125.11,
      "midp": 27.69
    },
    {
      "cfd": 124.82,
      "midp": 31.44
    },
    {
      "cfd": 123.27,
      "midp": 27.25
    },
    {
      "cfd": 123.01,
      "midp": 28.47
    },
    {
      "cfd": 124.68,
      "midp": 30.76
    },
    {
      "cfd": 126.34,
      "midp": 30.01
    },
    {
      "cfd": 128.46,
      "midp": 31.22
    },
    {
      "cfd": 129.27,
      "midp": 29.05
    },
    {
      "cfd": 130.08,
      "midp": 33.83
    },
    {
      "cfd": 130.22,
      "midp": 34.14
    },
    {
      "cfd": 130.55,
      "midp": 25.82
    },
    {
      "cfd": 131.33,
      "midp": 28.49
    },
    {
      "cfd": 132.46,
      "midp": 25.53
    },
    {
      "cfd": 132.82,
      "midp": 25.52
    },
    {
      "cfd": 133.46,
      "midp": 25.65
    },
    {
      "cfd": 134.67,
      "midp": 30.11
    },
    {
      "cfd": 134.16,
      "midp": 28.48
    },
    {
      "cfd": 135.81,
      "midp": 25.59
    },
    {
      "cfd": 136.79,
      "midp": 26.38
    },
    {
      "cfd": 136.26,
      "midp": 26.16
    },
    {
      "cfd": 136.13,
      "midp": 25.91
    },
    {
      "cfd": 136.38,
      "midp": 23.63
    },
    {
      "cfd": 137.24,
      "midp": 25.87
    },
    {
      "cfd": 137.04,
      "midp": 27.41
    },
    {
      "cfd": 136.02,
      "midp": 26.71
    },
    {
      "cfd": 135.27,
      "midp": 24.17
    },
    {
      "cfd": 136.31,
      "midp": 24.89
    },
    {
      "cfd": 136.1,
      "midp": 24.92
    },
    {
      "cfd": 136.55,
      "midp": 25.22
    },
    {
      "cfd": 137.98,
      "midp": 24.54
    },
    {
      "cfd": 139.93,
      "midp": 24.2
    },
    {
      "cfd": 140.3,
      "midp": 22.92
    },
    {
      "cfd": 140.68,
      "midp": 20.94
    },
    {
      "cfd": 140.96,
      "midp": 25.06
    },
    {
      "cfd": 140.79,
      "midp": 22.27
    },
    {
      "cfd": 141.9,
      "midp": 24.45
    },
    {
      "cfd": 141.24,
      "midp": 26.39
    },
    {
      "cfd": 140.91,
      "midp": 22.9
    },
    {
      "cfd": 141.46,
      "midp": 23.47
    },
    {
      "cfd": 142.23,
      "midp": 20.98
    },
    {
      "cfd": 141.68,
      "midp": 23.61
    },
    {
      "cfd": 142.27,
      "midp": 24.09
    },
    {
      "cfd": 142.55,
      "midp": 25.27
    },
    {
      "cfd": 142.39,
      "midp": 26.56
    },
    {
      "cfd": 142.66,
      "midp": 26.9
    },
    {
      "cfd": 142.78,
      "midp": 24.54
    },
    {
      "cfd": 142.63,
      "midp": 20.3
    }
  ],
  "periods": 48
}