{
  "settlementDate": {
    "year": 2022,
    "month": 10,
    "day": 31
  },
  "prices": [
    {
      "cfd": 172.26,
      "midp": 51.04
    },
    {
      "cfd": 171.44,
      "midp": 51.03
    },
    {
      "cfd": 171.03,
      "midp": 83.38
    },
    {
      "cfd": 170.93,
      "midp": 84.84
    },
    {
      "cfd": 171.21,
      "midp": 88.86
    },
    {
      "cfd": 171.49,
      "midp": 86.44
    },
    {
      "cfd": 171.94,
      "midp": 82.62
    },
    {
      "cfd": 172.06,
      "midp": 88.56
    },
    {
      "cfd": 171.21,
      "midp": 97.52
    },
    {
      "cfd": 171,
      "midp": 109.67
    },
    {
      "cfd": 171.93,
      "midp": 102.04
    },
    {
      "cfd": 172.78,
      "midp": 111.72
    },
    {
      "cfd": 171.89,
      "midp": 121.92
    },
    {
      "cfd": 171.85,
      "midp": 143.61
    },
    {
      "cfd": 171.44,
      "midp": 144.67
    },
    {
      "cfd": 171.36,
      "midp": 138.06
    },
    {
      "cfd": 170.9,
      "midp": 132.64
    },
    {
      "cfd": 170.91,
      "midp": 124.99
    },
    {
      "cfd": 172.26,
      "midp": 124.03
    },
    {
      "cfd": 172.5,
      "midp": 123.9
    },
    {
      "cfd": 171.76,
      "midp": 112.67
    },
    {
      "cfd": 172.09,
      "midp": 125.89
    },
    {
      "cfd": 171.67,
      "midp": 108.49
    },
    {
      "cfd": 171.22,
      "midp": 115.84
    },
    {
      "cfd": 170.65,
      "midp": 118.31
    },
    {
      "cfd": 170.59,
      "midp": 115.72
    },
    {
      "cfd": 170.02,
      "midp": 102.28
    },
    {
      "cfd": 171.49,
      "midp": 106.84
    },
    {
      "cfd": 171.27,
      "midp": 108.96
    },
    {
      "cfd": 171.94,
      "midp": 116.18
    },
    {
      "cfd": 172.24,
      "midp": 122.81
    },
    {
      "cfd": 170.82,
      "midp": 131.3
    },
    {
      "cfd": 169.55,
      "midp": 136.5
    },
    {
      "cfd": 168.68,
      "midp": 115.42
    },
    {
      "cfd": 167.34,
      "midp": 132.04
    },
    {
      "cfd": 167.75,
      "midp": 122.52
    },
    {
      "cfd": 169.51,
      "midp": 146.17
    },
    {
      "cfd": 170.05,
      "midp": 149.44
    },
    {
      "cfd": 169.67,
      "midp": 122.23
    },
    {
      "cfd": 169.69,
      "midp": 117.28
    },
    {
      "cfd": 169.36,
      "midp": 128.97
    },
    {
      "cfd": 170.71,
      "midp": 129.16
    },
    {
      "cfd": 170.51,
      "midp": 99.27
    },
    {
      "cfd": 170.57,
      "midp": 79.72
    },
    {
      "cfd": 170.51,
      "midp": 84.49
    },
    {
      "cfd": 170.56,
      "midp": 107.68
    },
    {
      "cfd": 170.13,
      "midp": 93.21
    },
    {
      "cfd": 170.38,
      "midp": 97.75
    }
  ],
  "periods": 48
}