{
  "settlementDate": {
    "year": 2022,
    "month": 5,
    "day": 6
  },
  "prices": [
    {
      "cfd": 162.04,
      "midp": 151.65
    },
    {
      "cfd": 162.52,
      "midp": 160.85
    },
    {
      "cfd": 163.94,
      "midp": 160.6
    },
    {
      "cfd": 164.74,
      "midp": 161.03
    },
    {
      "cfd": 165.55,
      "midp": 151.92
    },
    {
      "cfd": 166.16,
      "midp": 166.67
    },
    {
      "cfd": 165.86,
      "midp": 160.6
    },
    {
      "cfd": 164.73,
      "midp": 153.93
    },
    {
      "cfd": 164.48,
      "midp": 150.79
    },
    {
      "cfd": 164.5,
      "midp": 167
    },
    {
      "cfd": 164.33,
      "midp": 171.3
    },
    {
      "cfd": 163.28,
      "midp": 157.87
    },
    {
      "cfd": 163.63,
      "midp": 155.87
    },
    {
      "cfd": 165.69,
      "midp": 143.64
    },
    {
      "cfd": 165.57,
      "midp": 139.79
    },
    {
      "cfd": 163.3,
      "midp": 114.77
    },
    {
      "cfd": 162.4,
      "midp": 98.41
    },
    {
      "cfd": 162.19,
      "midp": 85.75
    },
    {
      "cfd": 162.43,
      "midp": 79.89
    },
    {
      "cfd": 161.05,
      "midp": 78.57
    },
    {
      "cfd": 160.03,
      "midp": 79.87
    },
    {
      "cfd": 157.03,
      "midp": 83.78
    },
    {
      "cfd": 156.84,
      "midp": 85.44
    },
    {
      "cfd": 157.13,
      "midp": 83.6
    },
    {
      "cfd": 158.35,
      "midp": 83.73
    },
    {
      "cfd": 160.5,
      "midp": 91.51
    },
    {
      "cfd": 163.21,
      "midp": 74.05
    },
    {
      "cfd": 162.05,
      "midp": 85.12
    },
    {
      "cfd": 161.62,
      "midp": 83.7
    },
    {
      "cfd": 161.04,
      "midp": 83.29
    },
    {
      "cfd": 159.38,
      "midp": 92.09
    },
    {
      "cfd": 157.38,
      "midp": 98.93
    },
    {
      "cfd": 157.62,
      "midp": 100.68
    },
    {
      "cfd": 156.6,
      "midp": 101.57
    },
    {
      "cfd": 154.24,
      "midp": 94.78
    },
    {
      "cfd": 150.63,
      "midp": 87.9
    },
    {
      "cfd": 152.42,
      "midp": 97.38
    },
    {
      "cfd": 152.82,
      "midp": 99.79
    },
    {
      "cfd": 150.14,
      "midp": 107.94
    },
    {
      "cfd": 149.48,
      "midp": 110.37
    },
    {
      "cfd": 152.57,
      "midp": 101.75
    },
    {
      "cfd": 155.09,
      "midp": 92.95
    },
    {
      "cfd": 155.67,
      "midp": 102.85
    },
    {
      "cfd": 155.08,
      "midp": 82.33
    },
    {
      "cfd": 156.08,
      "midp": 86.78
    },
    {
      "cfd": 157.15,
      "midp": 100.13
    },
    {
      "cfd": 159.99,
      "midp": 104.34
    },
    {
      "cfd": 161.09,
      "midp": 106.31
    }
  ],
  "periods": 48
}