{
  "settlementDate": {
    "year": 2025,
    "month": 6,
    "day": 6
  },
  "prices": [
    {
      "cfd": 152.24,
      "midp": 91.55
    },
    {
      "cfd": 146.34,
      "midp": 91.12
    },
    {
      "cfd": 144.97,
      "midp": 81.93
    },
    {
      "cfd": 145.37,
      "midp": 81.56
    },
    {
      "cfd": 147.83,
      "midp": 68.65
    },
    {
      "cfd": 151.23,
      "midp": 58.32
    },
    {
      "cfd": 154.44,
      "midp": 52.83
    },
    {
      "cfd": 156.89,
      "midp": 51.85
    },
    {
      "cfd": 154.72,
      "midp": 46.95
    },
    {
      "cfd": 165.43,
      "midp": 44.93
    },
    {
      "cfd": 174.52,
      "midp": 40.16
    },
    {
      "cfd": 157.9,
      "midp": 34.21
    },
    {
      "cfd": 149.64,
      "midp": 43.03
    },
    {
      "cfd": 151.88,
      "midp": 80.48
    },
    {
      "cfd": 158.92,
      "midp": 111.61
    },
    {
      "cfd": 160.5,
      "midp": 116.14
    },
    {
      "cfd": 158.11,
      "midp": 116.71
    },
    {
      "cfd": 156.56,
      "midp": 116.5
    },
    {
      "cfd": 157.22,
      "midp": 116.09
    },
    {
      "cfd": 159.07,
      "midp": 114.02
    },
    {
      "cfd": 159.66,
      "midp": 109.56
    },
    {
      "cfd": 159.04,
      "midp": 101.94
    },
    {
      "cfd": 159.19,
      "midp": 95.98
    },
    {
      "cfd": 155.23,
      "midp": 91.63
    },
    {
      "cfd": 158.83,
      "midp": 87.44
    },
    {
      "cfd": 158.68,
      "midp": 82.01
    },
    {
      "cfd": 154.97,
      "midp": 75.3
    },
    {
      "cfd": 150.15,
      "midp": 78.67
    },
    {
      "cfd": 149.95,
      "midp": 78.93
    },
    {
      "cfd": 151.43,
      "midp": 73.18
    },
    {
      "cfd": 152.57,
      "midp": 75.81
    },
    {
      "cfd": 153.34,
      "midp": 77.17
    },
    {
      "cfd": 156.04,
      "midp": 78.11
    },
    {
      "cfd": 154.31,
      "midp": 88.53
    },
    {
      "cfd": 153.63,
      "midp": 88.01
    },
    {
      "cfd": 152.36,
      "midp": 93.51
    },
    {
      "cfd": 154,
      "midp": 101.38
    },
    {
      "cfd": 159.89,
      "midp": 104.3
    },
    {
      "cfd": 161.09,
      "midp": 118.19
    },
    {
      "cfd": 161.98,
      "midp": 120.16
    },
    {
      "cfd": 162.51,
      "midp": 119.62
    },
    {
      "cfd": 154.55,
      "midp": 120.78
    },
    {
      "cfd": 146.4,
      "midp": 111.67
    },
    {
      "cfd": 149.45,
      "midp": 109.49
    },
    {
      "cfd": 157.21,
      "midp": 101.64
    },
    {
      "cfd": 156.13,
      "midp": 94.27
    },
    {
      "cfd": 149.51,
      "midp": 86.74
    },
    {
      "cfd": 150.54,
      "midp": 95.63
    }
  ],
  "periods": 48
}