{
  "settlementDate": {
    "year": 2020,
    "month": 1,
    "day": 25
  },
  "prices": [
    {
      "cfd": 139.94,
      "midp": 39.4
    },
    {
      "cfd": 142.82,
      "midp": 40.83
    },
    {
      "cfd": 141.67,
      "midp": 35.14
    },
    {
      "cfd": 145.69,
      "midp": 35.85
    },
    {
      "cfd": 145.05,
      "midp": 31.2
    },
    {
      "cfd": 145.65,
      "midp": 34
    },
    {
      "cfd": 145.98,
      "midp": 34.51
    },
    {
      "cfd": 146.16,
      "midp": 33.07
    },
    {
      "cfd": 146.71,
      "midp": 36.49
    },
    {
      "cfd": 147.16,
      "midp": 39.29
    },
    {
      "cfd": 148.03,
      "midp": 43.73
    },
    {
      "cfd": 146.98,
      "midp": 45.35
    },
    {
      "cfd": 143.7,
      "midp": 45.49
    },
    {
      "cfd": 141.75,
      "midp": 45.23
    },
    {
      "cfd": 141.6,
      "midp": 43.45
    },
    {
      "cfd": 143.15,
      "midp": 40.64
    },
    {
      "cfd": 145.13,
      "midp": 41.01
    },
    {
      "cfd": 146.06,
      "midp": 38.87
    },
    {
      "cfd": 147.77,
      "midp": 38.49
    },
    {
      "cfd": 147.18,
      "midp": 39.02
    },
    {
      "cfd": 146.93,
      "midp": 37.19
    },
    {
      "cfd": 147.15,
      "midp": 37.31
    },
    {
      "cfd": 147.64,
      "midp": 44.33
    },
    {
      "cfd": 147.5,
      "midp": 44.64
    },
    {
      "cfd": 148.44,
      "midp": 43.84
    },
    {
      "cfd": 148.65,
      "midp": 43.91
    },
    {
      "cfd": 148.83,
      "midp": 42.22
    },
    {
      "cfd": 148.2,
      "midp": 41.77
    },
    {
      "cfd": 148.08,
      "midp": 41.65
    },
    {
      "cfd": 149.35,
      "midp": 39.27
    },
    {
      "cfd": 149.19,
      "midp": 39.57
    },
    {
      "cfd": 148.93,
      "midp": 38.14
    },
    {
      "cfd": 147.32,
      "midp": 34.18
    },
    {
      "cfd": 147.47,
      "midp": 32.85
    },
    {
      "cfd": 146.6,
      "midp": 20.59
    },
    {
      "cfd": 148.84,
      "midp": 19.2
    },
    {
      "cfd": 148.85,
      "midp": 18.26
    },
    {
      "cfd": 148.02,
      "midp": 17.95
    },
    {
      "cfd": 149.2,
      "midp": 18.41
    },
    {
      "cfd": 151.26,
      "midp": 18.33
    },
    {
      "cfd": 150.92,
      "midp": 17.9
    },
    {
      "cfd": 151.12,
      "midp": 18.7
    },
    {
      "cfd": 150.9,
      "midp": 22.41
    },
    {
      "cfd": 151.14,
      "midp": 25.37
    },
    {
      "cfd": 151.55,
      "midp": 25.23
    },
    {
      "cfd": 150.88,
      "midp": 25.65
    },
    {
      "cfd": 149.5,
      "midp": 29.19
    },
    {
      "cfd": 148.92,
      "midp": 28
    }
  ],
  "periods": 48
}