{
  "settlementDate": {
    "year": 2023,
    "month": 10,
    "day": 18
  },
  "prices": [
    {
      "cfd": 167.7,
      "midp": 36.34
    },
    {
      "cfd": 168.73,
      "midp": 78.85
    },
    {
      "cfd": 168.37,
      "midp": 49.16
    },
    {
      "cfd": 168.08,
      "midp": 84.55
    },
    {
      "cfd": 168.01,
      "midp": 52.17
    },
    {
      "cfd": 167.6,
      "midp": 107.28
    },
    {
      "cfd": 167.69,
      "midp": 73.04
    },
    {
      "cfd": 167.81,
      "midp": 107.87
    },
    {
      "cfd": 168.22,
      "midp": 113.45
    },
    {
      "cfd": 168.16,
      "midp": 120.7
    },
    {
      "cfd": 168.24,
      "midp": 125.07
    },
    {
      "cfd": 168.23,
      "midp": 121.17
    },
    {
      "cfd": 167.92,
      "midp": 123.59
    },
    {
      "cfd": 166.46,
      "midp": 111.27
    },
    {
      "cfd": 164.77,
      "midp": 118.18
    },
    {
      "cfd": 163.78,
      "midp": 106.66
    },
    {
      "cfd": 163.71,
      "midp": 103.52
    },
    {
      "cfd": 164.49,
      "midp": 86.25
    },
    {
      "cfd": 165.09,
      "midp": 86.63
    },
    {
      "cfd": 164.07,
      "midp": 78.57
    },
    {
      "cfd": 163.42,
      "midp": 69.22
    },
    {
      "cfd": 163.37,
      "midp": 70.01
    },
    {
      "cfd": 163.39,
      "midp": 54.62
    },
    {
      "cfd": 162.83,
      "midp": 53.68
    },
    {
      "cfd": 162.61,
      "midp": 73.18
    },
    {
      "cfd": 162.56,
      "midp": 76.01
    },
    {
      "cfd": 162.19,
      "midp": 91.02
    },
    {
      "cfd": 162.45,
      "midp": 102.07
    },
    {
      "cfd": 162.4,
      "midp": 82.31
    },
    {
      "cfd": 162.29,
      "midp": 96.03
    },
    {
      "cfd": 162.46,
      "midp": 110.21
    },
    {
      "cfd": 161.82,
      "midp": 104.67
    },
    {
      "cfd": 161.62,
      "midp": 123.45
    },
    {
      "cfd": 161.72,
      "midp": 84.06
    },
    {
      "cfd": 161.52,
      "midp": 94.42
    },
    {
      "cfd": 161.24,
      "midp": 51.25
    },
    {
      "cfd": 161.35,
      "midp": 81.74
    },
    {
      "cfd": 161.79,
      "midp": 53.62
    },
    {
      "cfd": 162,
      "midp": 31.73
    },
    {
      "cfd": 161.84,
      "midp": 8.38
    },
    {
      "cfd": 161.76,
      "midp": 23.69
    },
    {
      "cfd": 161.98,
      "midp": 27.45
    },
    {
      "cfd": 162.14,
      "midp": 34.58
    },
    {
      "cfd": 162.28,
      "midp": 50.16
    },
    {
      "cfd": 162.42,
      "midp": 37.93
    },
    {
      "cfd": 162.83,
      "midp": 40.29
    },
    {
      "cfd": 164.3,
      "midp": 43.19
    },
    {
      "cfd": 166.13,
      "midp": 51.23
    }
  ],
  "periods": 48
}