{
  "settlementDate": {
    "year": 2022,
    "month": 8,
    "day": 15
  },
  "prices": [
    {
      "cfd": 139.92,
      "midp": 318.02
    },
    {
      "cfd": 141.76,
      "midp": 321.66
    },
    {
      "cfd": 140.66,
      "midp": 340.34
    },
    {
      "cfd": 137.7,
      "midp": 305.48
    },
    {
      "cfd": 136,
      "midp": 344.9
    },
    {
      "cfd": 133.23,
      "midp": 301.58
    },
    {
      "cfd": 131.79,
      "midp": 284.96
    },
    {
      "cfd": 140.44,
      "midp": 275.62
    },
    {
      "cfd": 147.45,
      "midp": 285.92
    },
    {
      "cfd": 150.4,
      "midp": 286.57
    },
    {
      "cfd": 155.89,
      "midp": 292.38
    },
    {
      "cfd": 151.86,
      "midp": 267.91
    },
    {
      "cfd": 147.08,
      "midp": 305.95
    },
    {
      "cfd": 143.84,
      "midp": 336.5
    },
    {
      "cfd": 139.71,
      "midp": 316.82
    },
    {
      "cfd": 137.78,
      "midp": 368.02
    },
    {
      "cfd": 136.24,
      "midp": 352.18
    },
    {
      "cfd": 132.62,
      "midp": 405.86
    },
    {
      "cfd": 131.21,
      "midp": 367.61
    },
    {
      "cfd": 131.02,
      "midp": 372.62
    },
    {
      "cfd": 132.86,
      "midp": 368.25
    },
    {
      "cfd": 139.99,
      "midp": 367.2
    },
    {
      "cfd": 139.26,
      "midp": 355.74
    },
    {
      "cfd": 136.1,
      "midp": 349.39
    },
    {
      "cfd": 134.42,
      "midp": 359.06
    },
    {
      "cfd": 136.49,
      "midp": 362.2
    },
    {
      "cfd": 137.36,
      "midp": 381.64
    },
    {
      "cfd": 139.43,
      "midp": 364.12
    },
    {
      "cfd": 142.66,
      "midp": 362.39
    },
    {
      "cfd": 144.33,
      "midp": 353
    },
    {
      "cfd": 141.55,
      "midp": 322.97
    },
    {
      "cfd": 140.45,
      "midp": 311.7
    },
    {
      "cfd": 138.97,
      "midp": 351.42
    },
    {
      "cfd": 144.01,
      "midp": 384.54
    },
    {
      "cfd": 148.31,
      "midp": 405.99
    },
    {
      "cfd": 146.39,
      "midp": 404.98
    },
    {
      "cfd": 141.76,
      "midp": 404.77
    },
    {
      "cfd": 139.17,
      "midp": 400.54
    },
    {
      "cfd": 139.98,
      "midp": 438.97
    },
    {
      "cfd": 143.47,
      "midp": 440.31
    },
    {
      "cfd": 145.35,
      "midp": 435.74
    },
    {
      "cfd": 145.14,
      "midp": 385.76
    },
    {
      "cfd": 145.11,
      "midp": 431.52
    },
    {
      "cfd": 142.88,
      "midp": 433.07
    },
    {
      "cfd": 142.12,
      "midp": 428.82
    },
    {
      "cfd": 144.47,
      "midp": 401.65
    },
    {
      "cfd": 147.07,
      "midp": 368.98
    },
    {
      "cfd": 153.56,
      "midp": 329.5
    }
  ],
  "periods": 48
}