{
  "settlementDate": {
    "year": 2022,
    "month": 6,
    "day": 15
  },
  "prices": [
    {
      "cfd": 141.28,
      "midp": 146.93
    },
    {
      "cfd": 141.11,
      "midp": 127.31
    },
    {
      "cfd": 142.01,
      "midp": 133.72
    },
    {
      "cfd": 144.5,
      "midp": 140.36
    },
    {
      "cfd": 144.1,
      "midp": 120.27
    },
    {
      "cfd": 142.84,
      "midp": 120.5
    },
    {
      "cfd": 143.16,
      "midp": 135.3
    },
    {
      "cfd": 142.12,
      "midp": 121.85
    },
    {
      "cfd": 141.88,
      "midp": 122.77
    },
    {
      "cfd": 140.64,
      "midp": 125.37
    },
    {
      "cfd": 138.83,
      "midp": 124.22
    },
    {
      "cfd": 137.5,
      "midp": 149.3
    },
    {
      "cfd": 137.9,
      "midp": 168.96
    },
    {
      "cfd": 139.04,
      "midp": 207.09
    },
    {
      "cfd": 137.46,
      "midp": 202.93
    },
    {
      "cfd": 135.72,
      "midp": 215.4
    },
    {
      "cfd": 136.28,
      "midp": 197.61
    },
    {
      "cfd": 136.1,
      "midp": 174.7
    },
    {
      "cfd": 136.21,
      "midp": 187.06
    },
    {
      "cfd": 135.48,
      "midp": 168.28
    },
    {
      "cfd": 134.72,
      "midp": 148.2
    },
    {
      "cfd": 133.87,
      "midp": 140.95
    },
    {
      "cfd": 134.38,
      "midp": 161.55
    },
    {
      "cfd": 136.41,
      "midp": 166.4
    },
    {
      "cfd": 137.17,
      "midp": 157.98
    },
    {
      "cfd": 137.16,
      "midp": 151.69
    },
    {
      "cfd": 137.15,
      "midp": 146.77
    },
    {
      "cfd": 137.94,
      "midp": 147.24
    },
    {
      "cfd": 138.59,
      "midp": 161.44
    },
    {
      "cfd": 139.89,
      "midp": 158.79
    },
    {
      "cfd": 140.52,
      "midp": 177.37
    },
    {
      "cfd": 141.84,
      "midp": 186.78
    },
    {
      "cfd": 142.66,
      "midp": 183.75
    },
    {
      "cfd": 143.05,
      "midp": 202.97
    },
    {
      "cfd": 142.71,
      "midp": 233.19
    },
    {
      "cfd": 142.63,
      "midp": 236.7
    },
    {
      "cfd": 141.28,
      "midp": 236.38
    },
    {
      "cfd": 142.4,
      "midp": 236.18
    },
    {
      "cfd": 144.88,
      "midp": 251.13
    },
    {
      "cfd": 145.13,
      "midp": 245.1
    },
    {
      "cfd": 145.27,
      "midp": 225.82
    },
    {
      "cfd": 145.29,
      "midp": 222.99
    },
    {
      "cfd": 146.76,
      "midp": 219.22
    },
    {
      "cfd": 147.18,
      "midp": 220.12
    },
    {
      "cfd": 147.58,
      "midp": 217.72
    },
    {
      "cfd": 148.2,
      "midp": 199.34
    },
    {
      "cfd": 147.56,
      "midp": 202.45
    },
    {
      "cfd": 147.29,
      "midp": 169.24
    }
  ],
  "periods": 48
}