{
  "settlementDate": {
    "year": 2023,
    "month": 6,
    "day": 23
  },
  "prices": [
    {
      "cfd": 162.84,
      "midp": 88.3
    },
    {
      "cfd": 166.19,
      "midp": 85.5
    },
    {
      "cfd": 171.62,
      "midp": 79.09
    },
    {
      "cfd": 171.06,
      "midp": 77.4
    },
    {
      "cfd": 168.74,
      "midp": 86.26
    },
    {
      "cfd": 172.23,
      "midp": 87.18
    },
    {
      "cfd": 171.6,
      "midp": 88.59
    },
    {
      "cfd": 173.9,
      "midp": 80.94
    },
    {
      "cfd": 175.83,
      "midp": 88.3
    },
    {
      "cfd": 170.93,
      "midp": 83.2
    },
    {
      "cfd": 175.27,
      "midp": 91.45
    },
    {
      "cfd": 178.24,
      "midp": 96.99
    },
    {
      "cfd": 174.38,
      "midp": 101.32
    },
    {
      "cfd": 174.26,
      "midp": 122.14
    },
    {
      "cfd": 178.81,
      "midp": 96.48
    },
    {
      "cfd": 173.6,
      "midp": 110.36
    },
    {
      "cfd": 175.07,
      "midp": 108.16
    },
    {
      "cfd": 175.68,
      "midp": 113.86
    },
    {
      "cfd": 179.79,
      "midp": 106.76
    },
    {
      "cfd": 174.06,
      "midp": 102.39
    },
    {
      "cfd": 173.59,
      "midp": 95.83
    },
    {
      "cfd": 173.55,
      "midp": 88.28
    },
    {
      "cfd": 169.77,
      "midp": 104.53
    },
    {
      "cfd": 158.46,
      "midp": 84.67
    },
    {
      "cfd": 152.38,
      "midp": 66.12
    },
    {
      "cfd": 152.15,
      "midp": 64.08
    },
    {
      "cfd": 157.89,
      "midp": 73.66
    },
    {
      "cfd": 163.77,
      "midp": 66.72
    },
    {
      "cfd": 166.87,
      "midp": 72.22
    },
    {
      "cfd": 169.99,
      "midp": 69.63
    },
    {
      "cfd": 171.64,
      "midp": 79.47
    },
    {
      "cfd": 170.55,
      "midp": 86.47
    },
    {
      "cfd": 170.1,
      "midp": 79.13
    },
    {
      "cfd": 171.55,
      "midp": 87.81
    },
    {
      "cfd": 170,
      "midp": 94.14
    },
    {
      "cfd": 173.03,
      "midp": 92.7
    },
    {
      "cfd": 175.96,
      "midp": 96.77
    },
    {
      "cfd": 177.34,
      "midp": 94.56
    },
    {
      "cfd": 180.01,
      "midp": 96.52
    },
    {
      "cfd": 178.12,
      "midp": 93.96
    },
    {
      "cfd": 177.74,
      "midp": 104.42
    },
    {
      "cfd": 177.09,
      "midp": 100.04
    },
    {
      "cfd": 178.65,
      "midp": 96.49
    },
    {
      "cfd": 176.73,
      "midp": 91.52
    },
    {
      "cfd": 172.01,
      "midp": 93.72
    },
    {
      "cfd": 173.26,
      "midp": 88.23
    },
    {
      "cfd": 178.95,
      "midp": 88.88
    },
    {
      "cfd": 178.74,
      "midp": 90.35
    }
  ],
  "periods": 48
}