{
  "settlementDate": {
    "year": 2024,
    "month": 8,
    "day": 7
  },
  "prices": [
    {
      "cfd": 151.56,
      "midp": 63.1
    },
    {
      "cfd": 146.98,
      "midp": 46.63
    },
    {
      "cfd": 145.44,
      "midp": 39.99
    },
    {
      "cfd": 141.04,
      "midp": 32.05
    },
    {
      "cfd": 140.78,
      "midp": 28.8
    },
    {
      "cfd": 143.38,
      "midp": 25.16
    },
    {
      "cfd": 141.39,
      "midp": 28.06
    },
    {
      "cfd": 140.75,
      "midp": 17.68
    },
    {
      "cfd": 143.11,
      "midp": 22.52
    },
    {
      "cfd": 144.02,
      "midp": 20.15
    },
    {
      "cfd": 145.04,
      "midp": 27.01
    },
    {
      "cfd": 145.28,
      "midp": 28.7
    },
    {
      "cfd": 149.18,
      "midp": 31.95
    },
    {
      "cfd": 150.73,
      "midp": 39.63
    },
    {
      "cfd": 152.22,
      "midp": 54.16
    },
    {
      "cfd": 150.85,
      "midp": 61.75
    },
    {
      "cfd": 151.79,
      "midp": 67.86
    },
    {
      "cfd": 152,
      "midp": 68.45
    },
    {
      "cfd": 148.44,
      "midp": 69.98
    },
    {
      "cfd": 150.33,
      "midp": 67.4
    },
    {
      "cfd": 152.81,
      "midp": 69.19
    },
    {
      "cfd": 151.43,
      "midp": 65.68
    },
    {
      "cfd": 152.79,
      "midp": 53.08
    },
    {
      "cfd": 151.28,
      "midp": 62.04
    },
    {
      "cfd": 150.13,
      "midp": 66.38
    },
    {
      "cfd": 149.93,
      "midp": 63.85
    },
    {
      "cfd": 148.95,
      "midp": 54.89
    },
    {
      "cfd": 148.63,
      "midp": 52.06
    },
    {
      "cfd": 148.91,
      "midp": 49.87
    },
    {
      "cfd": 150.97,
      "midp": 44.66
    },
    {
      "cfd": 152.58,
      "midp": 34.07
    },
    {
      "cfd": 153.82,
      "midp": 46.5
    },
    {
      "cfd": 154.07,
      "midp": 53.02
    },
    {
      "cfd": 154.49,
      "midp": 53.89
    },
    {
      "cfd": 151.5,
      "midp": 63.16
    },
    {
      "cfd": 153.35,
      "midp": 73.55
    },
    {
      "cfd": 151.15,
      "midp": 70.67
    },
    {
      "cfd": 151.67,
      "midp": 74.29
    },
    {
      "cfd": 152.42,
      "midp": 84.5
    },
    {
      "cfd": 150.9,
      "midp": 84.72
    },
    {
      "cfd": 151.08,
      "midp": 82.12
    },
    {
      "cfd": 155.16,
      "midp": 82.85
    },
    {
      "cfd": 157.12,
      "midp": 82.13
    },
    {
      "cfd": 155.06,
      "midp": 82.75
    },
    {
      "cfd": 155.4,
      "midp": 82.2
    },
    {
      "cfd": 155.67,
      "midp": 77.6
    },
    {
      "cfd": 153.69,
      "midp": 57.37
    },
    {
      "cfd": 152.73,
      "midp": 48.09
    }
  ],
  "periods": 48
}