{
  "settlementDate": {
    "year": 2020,
    "month": 6,
    "day": 25
  },
  "prices": [
    {
      "cfd": 143.37,
      "midp": 30.15
    },
    {
      "cfd": 142.95,
      "midp": 16.83
    },
    {
      "cfd": 142.81,
      "midp": 36.59
    },
    {
      "cfd": 143.13,
      "midp": 35.49
    },
    {
      "cfd": 142.75,
      "midp": 35.21
    },
    {
      "cfd": 143.02,
      "midp": 36.84
    },
    {
      "cfd": 143.05,
      "midp": 35.16
    },
    {
      "cfd": 142.95,
      "midp": 36.4
    },
    {
      "cfd": 143.2,
      "midp": 32.47
    },
    {
      "cfd": 143.65,
      "midp": 33.8
    },
    {
      "cfd": 144.28,
      "midp": 36.06
    },
    {
      "cfd": 143.91,
      "midp": 34.57
    },
    {
      "cfd": 142.14,
      "midp": 32.47
    },
    {
      "cfd": 140.49,
      "midp": 29.91
    },
    {
      "cfd": 140.48,
      "midp": 31.37
    },
    {
      "cfd": 142,
      "midp": 23.98
    },
    {
      "cfd": 141.76,
      "midp": 21.71
    },
    {
      "cfd": 141.12,
      "midp": 23.78
    },
    {
      "cfd": 141.33,
      "midp": 22.55
    },
    {
      "cfd": 141.1,
      "midp": 22.59
    },
    {
      "cfd": 141.44,
      "midp": 24.15
    },
    {
      "cfd": 141.62,
      "midp": 27.02
    },
    {
      "cfd": 141.77,
      "midp": 25.83
    },
    {
      "cfd": 141.57,
      "midp": 29.1
    },
    {
      "cfd": 141.44,
      "midp": 23.25
    },
    {
      "cfd": 141.57,
      "midp": 24.57
    },
    {
      "cfd": 141.77,
      "midp": 33.94
    },
    {
      "cfd": 141.73,
      "midp": 36.88
    },
    {
      "cfd": 143.05,
      "midp": 36.72
    },
    {
      "cfd": 143.79,
      "midp": 38.03
    },
    {
      "cfd": 143.55,
      "midp": 37.54
    },
    {
      "cfd": 143.79,
      "midp": 38.26
    },
    {
      "cfd": 144.05,
      "midp": 43.92
    },
    {
      "cfd": 144.09,
      "midp": 38
    },
    {
      "cfd": 143.86,
      "midp": 33.45
    },
    {
      "cfd": 144.3,
      "midp": 39.94
    },
    {
      "cfd": 143.95,
      "midp": 30.52
    },
    {
      "cfd": 144.08,
      "midp": 33.5
    },
    {
      "cfd": 143.76,
      "midp": 24.47
    },
    {
      "cfd": 144.4,
      "midp": 28.14
    },
    {
      "cfd": 145.88,
      "midp": 21.66
    },
    {
      "cfd": 146.76,
      "midp": 24.39
    },
    {
      "cfd": 146.08,
      "midp": 26.07
    },
    {
      "cfd": 145.92,
      "midp": 28.12
    },
    {
      "cfd": 145.13,
      "midp": 25.11
    },
    {
      "cfd": 143.36,
      "midp": 25.01
    },
    {
      "cfd": 141.44,
      "midp": 25.35
    },
    {
      "cfd": 140.85,
      "midp": 30.45
    }
  ],
  "periods": 48
}