{
  "settlementDate": {
    "year": 2021,
    "month": 11,
    "day": 16
  },
  "prices": [
    {
      "cfd": 126.93,
      "midp": 158.18
    },
    {
      "cfd": 128.59,
      "midp": 185.03
    },
    {
      "cfd": 130.16,
      "midp": 159.25
    },
    {
      "cfd": 129.49,
      "midp": 151.93
    },
    {
      "cfd": 132.91,
      "midp": 145.29
    },
    {
      "cfd": 134.82,
      "midp": 152.26
    },
    {
      "cfd": 132.96,
      "midp": 153.03
    },
    {
      "cfd": 134.47,
      "midp": 147.85
    },
    {
      "cfd": 132.05,
      "midp": 151.63
    },
    {
      "cfd": 133.38,
      "midp": 139.37
    },
    {
      "cfd": 132.33,
      "midp": 177.55
    },
    {
      "cfd": 131.09,
      "midp": 143.55
    },
    {
      "cfd": 130.78,
      "midp": 153.81
    },
    {
      "cfd": 131.53,
      "midp": 164.07
    },
    {
      "cfd": 132.55,
      "midp": 203.07
    },
    {
      "cfd": 136.35,
      "midp": 189.01
    },
    {
      "cfd": 137.2,
      "midp": 166.35
    },
    {
      "cfd": 138.12,
      "midp": 146.08
    },
    {
      "cfd": 139.9,
      "midp": 172.91
    },
    {
      "cfd": 140,
      "midp": 169.3
    },
    {
      "cfd": 141.26,
      "midp": 169.47
    },
    {
      "cfd": 142.97,
      "midp": 158.18
    },
    {
      "cfd": 144.05,
      "midp": 142.74
    },
    {
      "cfd": 144.76,
      "midp": 150.13
    },
    {
      "cfd": 145.45,
      "midp": 157.08
    },
    {
      "cfd": 145.22,
      "midp": 169.43
    },
    {
      "cfd": 144.22,
      "midp": 175.57
    },
    {
      "cfd": 144.35,
      "midp": 175.48
    },
    {
      "cfd": 145.8,
      "midp": 175.7
    },
    {
      "cfd": 148.33,
      "midp": 175.21
    },
    {
      "cfd": 148.46,
      "midp": 183.58
    },
    {
      "cfd": 147.92,
      "midp": 186.41
    },
    {
      "cfd": 147.86,
      "midp": 195.45
    },
    {
      "cfd": 148.28,
      "midp": 240.44
    },
    {
      "cfd": 148.18,
      "midp": 220.81
    },
    {
      "cfd": 149.8,
      "midp": 219.9
    },
    {
      "cfd": 151.25,
      "midp": 229.53
    },
    {
      "cfd": 152.8,
      "midp": 209.45
    },
    {
      "cfd": 153.67,
      "midp": 187.43
    },
    {
      "cfd": 153.8,
      "midp": 188.62
    },
    {
      "cfd": 152.87,
      "midp": 172.45
    },
    {
      "cfd": 152.46,
      "midp": 181.31
    },
    {
      "cfd": 152.26,
      "midp": 183.03
    },
    {
      "cfd": 151.27,
      "midp": 179.98
    },
    {
      "cfd": 148.87,
      "midp": 154.6
    },
    {
      "cfd": 147.56,
      "midp": 166.63
    },
    {
      "cfd": 148.17,
      "midp": 172.53
    },
    {
      "cfd": 148.77,
      "midp": 177.36
    }
  ],
  "periods": 48
}