{
  "settlementDate": {
    "year": 2021,
    "month": 4,
    "day": 18
  },
  "prices": [
    {
      "cfd": 128.53,
      "midp": 52.73
    },
    {
      "cfd": 128.3,
      "midp": 52.44
    },
    {
      "cfd": 128.75,
      "midp": 57.47
    },
    {
      "cfd": 129.23,
      "midp": 61.51
    },
    {
      "cfd": 130.94,
      "midp": 62.5
    },
    {
      "cfd": 132.63,
      "midp": 54.1
    },
    {
      "cfd": 131.92,
      "midp": 65.83
    },
    {
      "cfd": 130.54,
      "midp": 59.44
    },
    {
      "cfd": 133.77,
      "midp": 57.5
    },
    {
      "cfd": 131.74,
      "midp": 54.98
    },
    {
      "cfd": 130.6,
      "midp": 51.63
    },
    {
      "cfd": 130.71,
      "midp": 52.82
    },
    {
      "cfd": 130.51,
      "midp": 56.07
    },
    {
      "cfd": 130.46,
      "midp": 53.67
    },
    {
      "cfd": 130.65,
      "midp": 45.55
    },
    {
      "cfd": 131.22,
      "midp": 50.76
    },
    {
      "cfd": 131.1,
      "midp": 43.49
    },
    {
      "cfd": 129.91,
      "midp": 46.88
    },
    {
      "cfd": 129.51,
      "midp": 52.25
    },
    {
      "cfd": 129.02,
      "midp": 54.25
    },
    {
      "cfd": 128.94,
      "midp": 55
    },
    {
      "cfd": 128.22,
      "midp": 52.07
    },
    {
      "cfd": 127.78,
      "midp": 41.22
    },
    {
      "cfd": 128.67,
      "midp": 44.7
    },
    {
      "cfd": 128.97,
      "midp": 51.27
    },
    {
      "cfd": 128.28,
      "midp": 48.39
    },
    {
      "cfd": 127.03,
      "midp": 49.96
    },
    {
      "cfd": 127.37,
      "midp": 45.77
    },
    {
      "cfd": 126.43,
      "midp": 48.9
    },
    {
      "cfd": 125.79,
      "midp": 50.15
    },
    {
      "cfd": 124.59,
      "midp": 49.74
    },
    {
      "cfd": 124.17,
      "midp": 53.39
    },
    {
      "cfd": 122.83,
      "midp": 54.01
    },
    {
      "cfd": 121.68,
      "midp": 50.08
    },
    {
      "cfd": 120.7,
      "midp": 54.2
    },
    {
      "cfd": 119.74,
      "midp": 61.21
    },
    {
      "cfd": 119.53,
      "midp": 63.03
    },
    {
      "cfd": 119.88,
      "midp": 67.74
    },
    {
      "cfd": 120.13,
      "midp": 66.09
    },
    {
      "cfd": 119.64,
      "midp": 68.52
    },
    {
      "cfd": 119.33,
      "midp": 71.98
    },
    {
      "cfd": 119.06,
      "midp": 71.06
    },
    {
      "cfd": 119.44,
      "midp": 71.51
    },
    {
      "cfd": 119.82,
      "midp": 70.47
    },
    {
      "cfd": 119.8,
      "midp": 70.86
    },
    {
      "cfd": 119.78,
      "midp": 70.92
    },
    {
      "cfd": 121.19,
      "midp": 52.34
    },
    {
      "cfd": 123.17,
      "midp": 46.16
    }
  ],
  "periods": 48
}