{
  "settlementDate": {
    "year": 2021,
    "month": 6,
    "day": 12
  },
  "prices": [
    {
      "cfd": 141.4,
      "midp": 94.07
    },
    {
      "cfd": 141.71,
      "midp": 90.92
    },
    {
      "cfd": 141.44,
      "midp": 78.81
    },
    {
      "cfd": 140.89,
      "midp": 74.32
    },
    {
      "cfd": 140.84,
      "midp": 72.91
    },
    {
      "cfd": 138.5,
      "midp": 70.93
    },
    {
      "cfd": 137.25,
      "midp": 68.71
    },
    {
      "cfd": 136.92,
      "midp": 75.81
    },
    {
      "cfd": 138.3,
      "midp": 76.95
    },
    {
      "cfd": 137.55,
      "midp": 72.87
    },
    {
      "cfd": 139.47,
      "midp": 72.62
    },
    {
      "cfd": 140.11,
      "midp": 74.52
    },
    {
      "cfd": 140.71,
      "midp": 76.04
    },
    {
      "cfd": 139.98,
      "midp": 75.95
    },
    {
      "cfd": 139.94,
      "midp": 86.1
    },
    {
      "cfd": 139.89,
      "midp": 90.38
    },
    {
      "cfd": 140.91,
      "midp": 92.56
    },
    {
      "cfd": 143.38,
      "midp": 90.8
    },
    {
      "cfd": 144.3,
      "midp": 88.07
    },
    {
      "cfd": 144.08,
      "midp": 86.25
    },
    {
      "cfd": 143.54,
      "midp": 85.29
    },
    {
      "cfd": 142.85,
      "midp": 84.96
    },
    {
      "cfd": 142.35,
      "midp": 84.65
    },
    {
      "cfd": 141.34,
      "midp": 85.21
    },
    {
      "cfd": 141.42,
      "midp": 83.62
    },
    {
      "cfd": 140.35,
      "midp": 82.65
    },
    {
      "cfd": 140.84,
      "midp": 79.65
    },
    {
      "cfd": 140.96,
      "midp": 70.79
    },
    {
      "cfd": 140.61,
      "midp": 65.26
    },
    {
      "cfd": 136.95,
      "midp": 62.74
    },
    {
      "cfd": 134.13,
      "midp": 65.81
    },
    {
      "cfd": 133.19,
      "midp": 72.63
    },
    {
      "cfd": 129.98,
      "midp": 79.72
    },
    {
      "cfd": 126.85,
      "midp": 81.6
    },
    {
      "cfd": 126.19,
      "midp": 84.97
    },
    {
      "cfd": 125.8,
      "midp": 93.3
    },
    {
      "cfd": 124.7,
      "midp": 104.13
    },
    {
      "cfd": 124.82,
      "midp": 99.71
    },
    {
      "cfd": 124.54,
      "midp": 102.18
    },
    {
      "cfd": 123.57,
      "midp": 99.69
    },
    {
      "cfd": 124.31,
      "midp": 99.85
    },
    {
      "cfd": 125.88,
      "midp": 99.16
    },
    {
      "cfd": 127.35,
      "midp": 94.08
    },
    {
      "cfd": 128.74,
      "midp": 94.27
    },
    {
      "cfd": 129.47,
      "midp": 92.84
    },
    {
      "cfd": 131.36,
      "midp": 89.8
    },
    {
      "cfd": 133.3,
      "midp": 59.48
    },
    {
      "cfd": 136.65,
      "midp": 48.36
    }
  ],
  "periods": 48
}