{
  "settlementDate": {
    "year": 2024,
    "month": 7,
    "day": 24
  },
  "prices": [
    {
      "cfd": 145.3,
      "midp": 74.41
    },
    {
      "cfd": 144.86,
      "midp": 70.2
    },
    {
      "cfd": 144.56,
      "midp": 67.48
    },
    {
      "cfd": 141.31,
      "midp": 64.16
    },
    {
      "cfd": 142.28,
      "midp": 75.81
    },
    {
      "cfd": 142.1,
      "midp": 70.86
    },
    {
      "cfd": 138.78,
      "midp": 67.09
    },
    {
      "cfd": 139.72,
      "midp": 66.35
    },
    {
      "cfd": 140.05,
      "midp": 65.7
    },
    {
      "cfd": 139.51,
      "midp": 64.04
    },
    {
      "cfd": 140.44,
      "midp": 64.68
    },
    {
      "cfd": 140.98,
      "midp": 64.56
    },
    {
      "cfd": 140.33,
      "midp": 65.03
    },
    {
      "cfd": 140.77,
      "midp": 78.24
    },
    {
      "cfd": 141,
      "midp": 97.42
    },
    {
      "cfd": 140.21,
      "midp": 99.56
    },
    {
      "cfd": 140.35,
      "midp": 101.91
    },
    {
      "cfd": 139.1,
      "midp": 102.79
    },
    {
      "cfd": 138.42,
      "midp": 101.21
    },
    {
      "cfd": 138.3,
      "midp": 98.77
    },
    {
      "cfd": 137.81,
      "midp": 97.05
    },
    {
      "cfd": 138.01,
      "midp": 89.27
    },
    {
      "cfd": 139.24,
      "midp": 77.22
    },
    {
      "cfd": 140.32,
      "midp": 78.14
    },
    {
      "cfd": 140.68,
      "midp": 77.13
    },
    {
      "cfd": 141.34,
      "midp": 72.94
    },
    {
      "cfd": 144.87,
      "midp": 72.05
    },
    {
      "cfd": 143.33,
      "midp": 70.35
    },
    {
      "cfd": 142.28,
      "midp": 67.94
    },
    {
      "cfd": 140.64,
      "midp": 64.83
    },
    {
      "cfd": 139.55,
      "midp": 62.72
    },
    {
      "cfd": 137.25,
      "midp": 62.41
    },
    {
      "cfd": 137.13,
      "midp": 62.22
    },
    {
      "cfd": 137.37,
      "midp": 62.32
    },
    {
      "cfd": 137.19,
      "midp": 63.14
    },
    {
      "cfd": 136.96,
      "midp": 61.13
    },
    {
      "cfd": 136.41,
      "midp": 67.79
    },
    {
      "cfd": 135.89,
      "midp": 64.73
    },
    {
      "cfd": 136.86,
      "midp": 79.74
    },
    {
      "cfd": 139.25,
      "midp": 77.51
    },
    {
      "cfd": 142.08,
      "midp": 86.44
    },
    {
      "cfd": 143.88,
      "midp": 86.05
    },
    {
      "cfd": 142.35,
      "midp": 90.45
    },
    {
      "cfd": 144.25,
      "midp": 87.06
    },
    {
      "cfd": 145.01,
      "midp": 83.37
    },
    {
      "cfd": 144.94,
      "midp": 78.01
    },
    {
      "cfd": 144.44,
      "midp": 67.8
    },
    {
      "cfd": 146.1,
      "midp": 81.12
    }
  ],
  "periods": 48
}